napari_video/__init__.py
napari_video/napari.yaml
napari_video/napari_video.py
napari_video-0.2.13.dist-info/entry_points.txt
napari_video-0.2.13.dist-info/licenses/LICENSE
napari_video-0.2.13.dist-info/WHEEL
napari_video-0.2.13.dist-info/METADATA
napari_video-0.2.13.dist-info/RECORD
