Metadata-Version: 2.4
Name: napari_video
Version: 0.2.13
Summary: napari plugin for reading videos.
Home-page: https://github.com/janclemenslab/napari-video
Author: Jan Clemens
Author-email: clemensjan@googlemail.com
Requires-Python: >=3.6
Classifier: License :: OSI Approved :: MIT License
Classifier: Framework :: napari
Classifier: Operating System :: OS Independent
License-File: LICENSE
Requires-Dist: numpy
Requires-Dist: pyvideoreader
Project-URL: Bug Tracker, https://github.com/janclemenslab/napari-video/issues
Project-URL: Documentation, https://github.com/janclemenslab/napari-video/blob/main/README.md
Project-URL: Source Code, https://github.com/janclemenslab/napari-video
Project-URL: User Support, https://github.com/janclemenslab/napari-video/issues
